{
    "plugins": {
        "authorization": {
            "plugin": "mesosphere.marathon.plugin.auth.Authorizer",
            "implementation": "io.containx.marathon.plugin.auth.LDAPAuthorizor"
        },
        "authentication": {
            "plugin": "mesosphere.marathon.plugin.auth.Authenticator",
            "implementation": "io.containx.marathon.plugin.auth.LDAPAuthenticator",
            "configuration": {
                "ldap": {
                    "url": "ldap://my.ldapserver.local:389",
                    "base": "dc=example,dc=com",
                    "dn": "uid={username}",
                    "bindUser": "usernameToBind",
                    "bindPassword": "passwordToBind",
                    "userSearch": "(&(uid={username})(objectClass=inetOrgPerson))",
                    "userSubTree": "ou=People",
                    "groupSearch": "(&(memberUid={username})(objectClass=posixGroup))",
                    "groupSubTree": "ou=Group",
                    "ldapConnectTimeout": 3000,
                    "ldapReadTimeout": 3000
                },
                "users": [
                    {
                        "username": "someuser",
                        "password": "somepass",
                        "groups": [
                            "Admin"
                        ]
                    }
                ],
                "authorization": {
                    "access": [
                        {
                            "group": "Admin",
                            "permissions": [
                                {
                                    "allowed": "*",
                                    "type"   : "app"
                                },
                                {
                                    "allowed": "*",
                                    "type"   : "group"
                                }
                            ]
                        },
                        {
                            "group": "Developers",
                            "permissions": [
                                {
                                    "allowed": "view",
                                    "type": "app",
                                    "path": "/"
                                },
                                {
                                    "allowed": "view",
                                    "type": "group",
                                    "path": "/"
                                },
                                {
                                    "allowed": "create",
                                    "type": "app",
                                    "path": "/dev"
                                },
                                {
                                    "allowed": "update",
                                    "type": "app",
                                    "path": "/dev"
                                },
                                {
                                    "allowed": "delete",
                                    "type": "app",
                                    "path": "/dev"
                                }
                            ]
                        }
                    ]
                }
            }
        }
    }
}
